fns/__init__.py
fns/all.py
fns/cluster.py
fns/colab.py
fns/constants.py
fns/dataframe.py
fns/decorators.py
fns/exceptions.py
fns/feature_extraction.py
fns/fns.py
fns/json_encoders.py
fns/lexicon.py
fns/metrics.py
fns/model_selection.py
fns/multi_label.py
fns/notebook.py
fns/plot.py
fns/preprocessing.py
fns/streamlit_utils.py
fns/text.py
fns/vision.py
fns/baseline/__init__.py
fns/baseline/text_classification.py
fns-0.5.22.dist-info/LICENSE
fns-0.5.22.dist-info/METADATA
fns-0.5.22.dist-info/WHEEL
fns-0.5.22.dist-info/top_level.txt
fns-0.5.22.dist-info/RECORD
