Metadata-Version: 2.1
Name: fns
Version: 0.5.22
Summary: Reusable functions for use in ML projects
Home-page: https://github.com/amitness/fns
Author: Amit Chaudhary
Author-email: meamitkc@gmail.com
License: MIT
Platform: UNKNOWN
Classifier: Development Status :: 3 - Alpha
Classifier: Intended Audience :: Developers
Classifier: Topic :: Software Development :: Build Tools
Classifier: License :: OSI Approved :: MIT License
Classifier: Programming Language :: Python :: 3
Requires-Python: >=3.7
Requires-Dist: numpy
